Combinational/full_adder/full_adder.v
module full_adder (
    input A,
    input B,
    input Cin,
    output Sum,
    output Cout
);

assign Sum = A ^ B ^ Cin;
assign Cout = (A & B) | (Cin & (A ^ B));

endmodule

Combinational/full_adder/full_adder_tb.v
module full_adder_tb;

reg A;
reg B;
reg Cin;

wire Sum;
wire Cout;

full_adder dut(
    .A(A),
    .B(B),
    .Cin(Cin),
    .Sum(Sum),
    .Cout(Cout)
);

integer a;
integer b;
integer cin;

initial begin

    $dumpfile("full_adder.vcd");
    $dumpvars(0, full_adder_tb);

    for (a = 0; a <= 1; a = a + 1) begin
        for (b = 0; b <= 1; b = b + 1) begin
            for (cin = 0; cin <= 1; cin = cin + 1) begin

                A = a;
                B = b;
                Cin = cin;

                #10;

                $display(
                    "A = %b B = %b Cin = %b | Sum = %b Cout = %b",
                    A, B, Cin, Sum, Cout
                );

            end
        end
    end

    $finish;

end

endmodule

Combinational/full_adder/full_adder.vcd
$date
	Tue Aug 25 16:18:47 2026
$end
$version
	Icarus Verilog
$end
$timescale
	1s
$end
$scope module full_adder_tb $end
$var wire 1 ! Sum $end
$var wire 1 " Cout $end
$var reg 1 # A $end
$var reg 1 $ B $end
$var reg 1 % Cin $end
$var integer 32 & a [31:0] $end
$var integer 32 ' b [31:0] $end
$var integer 32 ( cin [31:0] $end
$scope module dut $end
$var wire 1 # A $end
$var wire 1 $ B $end
$var wire 1 % Cin $end
$var wire 1 " Cout $end
$var wire 1 ! Sum $end
$upscope $end
$upscope $end
$enddefinitions $end
$comment Show the parameter values. $end
$dumpall
$end
#0
$dumpvars
b0 (
b0 '
b0 &
0%
0$
0#
0"
0!
$end
#10
1!
1%
b1 (
#20
0%
1$
b1 '
b0 (
#30
1"
0!
1%
b1 (
#40
0"
1!
0%
0$
1#
b1 &
b0 '
b0 (
#50
1"
0!
1%
b1 (
#60
0%
1$
b1 '
b0 (
#70
1!
1%
b1 (
#80
b10 &
b10 '
b10 (
