Sequential/flip_flop/d_ff/d_ff.v
module d_ff (
    input wire clk,
    input wire d,
    output reg q
);

always @(posedge clk) begin
    q<=d;
end

endmodule

Sequential/flip_flop/d_ff/d_ff_tb.v
module d_ff_tb;

reg clk;
reg d;
wire q;

d_ff dut (
    .clk(clk),
    .d(d),
    .q(q)
);

always #5 clk = ~clk;

initial begin
    clk = 0;
    d = 0;

    #10 d = 1;
    #10 d = 0;
    #10 d = 1;
    #10 d = 0;

    #10 $finish;
end

initial begin
    $dumpfile("d_ff.vcd");
    $dumpvars(0, d_ff_tb);
end
endmodule

Sequential/flip_flop/d_ff/d_ff.vcd
$date
	Tue Sep  8 16:54:15 2026
$end
$version
	Icarus Verilog
$end
$timescale
	1s
$end
$scope module d_ff_tb $end
$var wire 1 ! q $end
$var reg 1 " clk $end
$var reg 1 # d $end
$scope module dut $end
$var wire 1 " clk $end
$var wire 1 # d $end
$var reg 1 ! q $end
$upscope $end
$upscope $end
$enddefinitions $end
$comment Show the parameter values. $end
$dumpall
$end
#0
$dumpvars
0#
0"
x!
$end
#5
0!
1"
#10
0"
1#
#15
1!
1"
#20
0"
0#
#25
0!
1"
#30
0"
1#
#35
1!
1"
#40
0"
0#
#45
0!
1"
