Sequential/flip_flop/jk_flipflop/jk_ff.v
module jk_ff (
    input J,
    input K,
    input clk,
    output reg Q
);

    always @(posedge clk) begin
        if (J == 0 && K == 0)
            Q <= Q;
        else if (J == 0 && K == 1)
            Q <= 0;
        else if (J == 1 && K == 0)
            Q <= 1;
        else
            Q <= ~Q;
    end

endmodule

Sequential/flip_flop/jk_flipflop/jk_ff_tb.v
module jk_ff_tb;

    reg J;
    reg K;
    reg clk;
    wire Q;

    jk_ff dut (
        .J(J),
        .K(K),
        .clk(clk),
        .Q(Q)
    );

    initial begin
        $dumpfile("jk_ff.vcd");
        $dumpvars(0, jk_ff_tb);

        clk = 0;
        J = 0;
        K = 0;

        #10;

        J = 0;
        K = 1;

        #10;

        J = 1;
        K = 0;

        #10;

        J = 1;
        K = 1;

        #20;

        $finish;
    end

    always #5 clk = ~clk;

endmodule

Sequential/flip_flop/jk_flipflop/jk_ff.vcd
$date
	Sun Sep  6 16:23:23 2026
$end
$version
	Icarus Verilog
$end
$timescale
	1s
$end
$scope module jk_ff_tb $end
$var wire 1 ! Q $end
$var reg 1 " J $end
$var reg 1 # K $end
$var reg 1 $ clk $end
$scope module dut $end
$var wire 1 " J $end
$var wire 1 # K $end
$var wire 1 $ clk $end
$var reg 1 ! Q $end
$upscope $end
$upscope $end
$enddefinitions $end
$comment Show the parameter values. $end
$dumpall
$end
#0
$dumpvars
0$
0#
0"
x!
$end
#5
1$
#10
0$
1#
#15
0!
1$
#20
0$
0#
1"
#25
1!
1$
#30
0$
1#
#35
0!
1$
#40
0$
#45
1!
1$
